{
  "version": "5",
  "dialect": "mysql",
  "id": "134e9a21-08d7-4821-aa2b-7763ee296ae8",
  "prevId": "5855d3ec-5b53-4c32-9746-b1f6b23efd06",
  "tables": {
    "arguments": {
      "name": "arguments",
      "columns": {
        "id": {
          "name": "id",
          "type": "int",
          "primaryKey": false,
          "notNull": true,
          "autoincrement": true
        },
        "userId": {
          "name": "userId",
          "type": "int",
          "primaryKey": false,
          "notNull": true,
          "autoincrement": false
        },
        "title": {
          "name": "title",
          "type": "varchar(255)",
          "primaryKey": false,
          "notNull": true,
          "autoincrement": false
        },
        "content": {
          "name": "content",
          "type": "text",
          "primaryKey": false,
          "notNull": true,
          "autoincrement": false
        },
        "position": {
          "name": "position",
          "type": "int",
          "primaryKey": false,
          "notNull": true,
          "autoincrement": false
        },
        "politicalSpectrum": {
          "name": "politicalSpectrum",
          "type": "int",
          "primaryKey": false,
          "notNull": false,
          "autoincrement": false
        },
        "category": {
          "name": "category",
          "type": "varchar(100)",
          "primaryKey": false,
          "notNull": false,
          "autoincrement": false
        },
        "upvotes": {
          "name": "upvotes",
          "type": "int",
          "primaryKey": false,
          "notNull": false,
          "autoincrement": false,
          "default": 0
        },
        "createdAt": {
          "name": "createdAt",
          "type": "timestamp",
          "primaryKey": false,
          "notNull": true,
          "autoincrement": false,
          "default": "(now())"
        },
        "updatedAt": {
          "name": "updatedAt",
          "type": "timestamp",
          "primaryKey": false,
          "notNull": true,
          "autoincrement": false,
          "onUpdate": true,
          "default": "(now())"
        }
      },
      "indexes": {
        "arguments_userId_idx": {
          "name": "arguments_userId_idx",
          "columns": [
            "userId"
          ],
          "isUnique": false
        },
        "arguments_position_idx": {
          "name": "arguments_position_idx",
          "columns": [
            "position"
          ],
          "isUnique": false
        }
      },
      "foreignKeys": {},
      "compositePrimaryKeys": {
        "arguments_id": {
          "name": "arguments_id",
          "columns": [
            "id"
          ]
        }
      },
      "uniqueConstraints": {},
      "checkConstraint": {}
    },
    "cases": {
      "name": "cases",
      "columns": {
        "id": {
          "name": "id",
          "type": "int",
          "primaryKey": false,
          "notNull": true,
          "autoincrement": true
        },
        "userId": {
          "name": "userId",
          "type": "int",
          "primaryKey": false,
          "notNull": true,
          "autoincrement": false
        },
        "caseType": {
          "name": "caseType",
          "type": "enum('Beitragsbescheid','Mahnung','Vollstreckung','Härtefall','Umzug','Befreiung','Treuhand','Schadensersatz','Sonstiges')",
          "primaryKey": false,
          "notNull": true,
          "autoincrement": false
        },
        "title": {
          "name": "title",
          "type": "varchar(255)",
          "primaryKey": false,
          "notNull": true,
          "autoincrement": false
        },
        "description": {
          "name": "description",
          "type": "text",
          "primaryKey": false,
          "notNull": false,
          "autoincrement": false
        },
        "status": {
          "name": "status",
          "type": "enum('Neu','In Bearbeitung','Widerspruch eingereicht','Anwalt konsultiert','Abgeschlossen','Archiviert')",
          "primaryKey": false,
          "notNull": true,
          "autoincrement": false,
          "default": "'Neu'"
        },
        "amount": {
          "name": "amount",
          "type": "decimal(10,2)",
          "primaryKey": false,
          "notNull": false,
          "autoincrement": false
        },
        "currency": {
          "name": "currency",
          "type": "varchar(3)",
          "primaryKey": false,
          "notNull": false,
          "autoincrement": false,
          "default": "'EUR'"
        },
        "receivedDate": {
          "name": "receivedDate",
          "type": "timestamp",
          "primaryKey": false,
          "notNull": false,
          "autoincrement": false
        },
        "deadline": {
          "name": "deadline",
          "type": "timestamp",
          "primaryKey": false,
          "notNull": false,
          "autoincrement": false
        },
        "assignedLawyerId": {
          "name": "assignedLawyerId",
          "type": "int",
          "primaryKey": false,
          "notNull": false,
          "autoincrement": false
        },
        "createdAt": {
          "name": "createdAt",
          "type": "timestamp",
          "primaryKey": false,
          "notNull": true,
          "autoincrement": false,
          "default": "(now())"
        },
        "updatedAt": {
          "name": "updatedAt",
          "type": "timestamp",
          "primaryKey": false,
          "notNull": true,
          "autoincrement": false,
          "onUpdate": true,
          "default": "(now())"
        }
      },
      "indexes": {
        "cases_userId_idx": {
          "name": "cases_userId_idx",
          "columns": [
            "userId"
          ],
          "isUnique": false
        },
        "cases_caseType_idx": {
          "name": "cases_caseType_idx",
          "columns": [
            "caseType"
          ],
          "isUnique": false
        },
        "cases_status_idx": {
          "name": "cases_status_idx",
          "columns": [
            "status"
          ],
          "isUnique": false
        }
      },
      "foreignKeys": {},
      "compositePrimaryKeys": {
        "cases_id": {
          "name": "cases_id",
          "columns": [
            "id"
          ]
        }
      },
      "uniqueConstraints": {},
      "checkConstraint": {}
    },
    "communityPosts": {
      "name": "communityPosts",
      "columns": {
        "id": {
          "name": "id",
          "type": "int",
          "primaryKey": false,
          "notNull": true,
          "autoincrement": true
        },
        "userId": {
          "name": "userId",
          "type": "int",
          "primaryKey": false,
          "notNull": true,
          "autoincrement": false
        },
        "title": {
          "name": "title",
          "type": "varchar(255)",
          "primaryKey": false,
          "notNull": true,
          "autoincrement": false
        },
        "content": {
          "name": "content",
          "type": "text",
          "primaryKey": false,
          "notNull": true,
          "autoincrement": false
        },
        "category": {
          "name": "category",
          "type": "enum('Erfahrungsbericht','Frage','Tipp','Ressource','Erfolgsgeschichte','Diskussion')",
          "primaryKey": false,
          "notNull": true,
          "autoincrement": false
        },
        "tags": {
          "name": "tags",
          "type": "json",
          "primaryKey": false,
          "notNull": false,
          "autoincrement": false
        },
        "sentiment": {
          "name": "sentiment",
          "type": "enum('positiv','neutral','negativ')",
          "primaryKey": false,
          "notNull": false,
          "autoincrement": false
        },
        "upvotes": {
          "name": "upvotes",
          "type": "int",
          "primaryKey": false,
          "notNull": false,
          "autoincrement": false,
          "default": 0
        },
        "downvotes": {
          "name": "downvotes",
          "type": "int",
          "primaryKey": false,
          "notNull": false,
          "autoincrement": false,
          "default": 0
        },
        "commentCount": {
          "name": "commentCount",
          "type": "int",
          "primaryKey": false,
          "notNull": false,
          "autoincrement": false,
          "default": 0
        },
        "createdAt": {
          "name": "createdAt",
          "type": "timestamp",
          "primaryKey": false,
          "notNull": true,
          "autoincrement": false,
          "default": "(now())"
        },
        "updatedAt": {
          "name": "updatedAt",
          "type": "timestamp",
          "primaryKey": false,
          "notNull": true,
          "autoincrement": false,
          "onUpdate": true,
          "default": "(now())"
        }
      },
      "indexes": {
        "communityPosts_userId_idx": {
          "name": "communityPosts_userId_idx",
          "columns": [
            "userId"
          ],
          "isUnique": false
        },
        "communityPosts_category_idx": {
          "name": "communityPosts_category_idx",
          "columns": [
            "category"
          ],
          "isUnique": false
        }
      },
      "foreignKeys": {},
      "compositePrimaryKeys": {
        "communityPosts_id": {
          "name": "communityPosts_id",
          "columns": [
            "id"
          ]
        }
      },
      "uniqueConstraints": {},
      "checkConstraint": {}
    },
    "dataRoomFiles": {
      "name": "dataRoomFiles",
      "columns": {
        "id": {
          "name": "id",
          "type": "int",
          "primaryKey": false,
          "notNull": true,
          "autoincrement": true
        },
        "dataRoomId": {
          "name": "dataRoomId",
          "type": "int",
          "primaryKey": false,
          "notNull": true,
          "autoincrement": false
        },
        "filename": {
          "name": "filename",
          "type": "varchar(255)",
          "primaryKey": false,
          "notNull": true,
          "autoincrement": false
        },
        "s3Key": {
          "name": "s3Key",
          "type": "varchar(512)",
          "primaryKey": false,
          "notNull": true,
          "autoincrement": false
        },
        "s3Url": {
          "name": "s3Url",
          "type": "varchar(512)",
          "primaryKey": false,
          "notNull": false,
          "autoincrement": false
        },
        "fileType": {
          "name": "fileType",
          "type": "varchar(100)",
          "primaryKey": false,
          "notNull": false,
          "autoincrement": false
        },
        "fileSize": {
          "name": "fileSize",
          "type": "int",
          "primaryKey": false,
          "notNull": false,
          "autoincrement": false
        },
        "uploadedBy": {
          "name": "uploadedBy",
          "type": "int",
          "primaryKey": false,
          "notNull": true,
          "autoincrement": false
        },
        "createdAt": {
          "name": "createdAt",
          "type": "timestamp",
          "primaryKey": false,
          "notNull": true,
          "autoincrement": false,
          "default": "(now())"
        }
      },
      "indexes": {
        "dataRoomFiles_dataRoomId_idx": {
          "name": "dataRoomFiles_dataRoomId_idx",
          "columns": [
            "dataRoomId"
          ],
          "isUnique": false
        }
      },
      "foreignKeys": {},
      "compositePrimaryKeys": {
        "dataRoomFiles_id": {
          "name": "dataRoomFiles_id",
          "columns": [
            "id"
          ]
        }
      },
      "uniqueConstraints": {},
      "checkConstraint": {}
    },
    "dataRooms": {
      "name": "dataRooms",
      "columns": {
        "id": {
          "name": "id",
          "type": "int",
          "primaryKey": false,
          "notNull": true,
          "autoincrement": true
        },
        "caseId": {
          "name": "caseId",
          "type": "int",
          "primaryKey": false,
          "notNull": true,
          "autoincrement": false
        },
        "userId": {
          "name": "userId",
          "type": "int",
          "primaryKey": false,
          "notNull": true,
          "autoincrement": false
        },
        "name": {
          "name": "name",
          "type": "varchar(255)",
          "primaryKey": false,
          "notNull": true,
          "autoincrement": false
        },
        "description": {
          "name": "description",
          "type": "text",
          "primaryKey": false,
          "notNull": false,
          "autoincrement": false
        },
        "createdAt": {
          "name": "createdAt",
          "type": "timestamp",
          "primaryKey": false,
          "notNull": true,
          "autoincrement": false,
          "default": "(now())"
        },
        "updatedAt": {
          "name": "updatedAt",
          "type": "timestamp",
          "primaryKey": false,
          "notNull": true,
          "autoincrement": false,
          "onUpdate": true,
          "default": "(now())"
        }
      },
      "indexes": {
        "dataRooms_caseId_idx": {
          "name": "dataRooms_caseId_idx",
          "columns": [
            "caseId"
          ],
          "isUnique": false
        },
        "dataRooms_userId_idx": {
          "name": "dataRooms_userId_idx",
          "columns": [
            "userId"
          ],
          "isUnique": false
        }
      },
      "foreignKeys": {},
      "compositePrimaryKeys": {
        "dataRooms_id": {
          "name": "dataRooms_id",
          "columns": [
            "id"
          ]
        }
      },
      "uniqueConstraints": {},
      "checkConstraint": {}
    },
    "documents": {
      "name": "documents",
      "columns": {
        "id": {
          "name": "id",
          "type": "int",
          "primaryKey": false,
          "notNull": true,
          "autoincrement": true
        },
        "caseId": {
          "name": "caseId",
          "type": "int",
          "primaryKey": false,
          "notNull": true,
          "autoincrement": false
        },
        "userId": {
          "name": "userId",
          "type": "int",
          "primaryKey": false,
          "notNull": true,
          "autoincrement": false
        },
        "filename": {
          "name": "filename",
          "type": "varchar(255)",
          "primaryKey": false,
          "notNull": true,
          "autoincrement": false
        },
        "documentType": {
          "name": "documentType",
          "type": "enum('Beitragsbescheid','Mahnung','Vollstreckungsbescheid','Widerspruch','Auskunftsersuchen','Härtefallantrag','Anwaltsschreiben','Sonstiges')",
          "primaryKey": false,
          "notNull": true,
          "autoincrement": false
        },
        "s3Key": {
          "name": "s3Key",
          "type": "varchar(512)",
          "primaryKey": false,
          "notNull": true,
          "autoincrement": false
        },
        "s3Url": {
          "name": "s3Url",
          "type": "varchar(512)",
          "primaryKey": false,
          "notNull": false,
          "autoincrement": false
        },
        "mimeType": {
          "name": "mimeType",
          "type": "varchar(100)",
          "primaryKey": false,
          "notNull": false,
          "autoincrement": false
        },
        "fileSize": {
          "name": "fileSize",
          "type": "int",
          "primaryKey": false,
          "notNull": false,
          "autoincrement": false
        },
        "extractedData": {
          "name": "extractedData",
          "type": "json",
          "primaryKey": false,
          "notNull": false,
          "autoincrement": false
        },
        "createdAt": {
          "name": "createdAt",
          "type": "timestamp",
          "primaryKey": false,
          "notNull": true,
          "autoincrement": false,
          "default": "(now())"
        },
        "updatedAt": {
          "name": "updatedAt",
          "type": "timestamp",
          "primaryKey": false,
          "notNull": true,
          "autoincrement": false,
          "onUpdate": true,
          "default": "(now())"
        }
      },
      "indexes": {
        "documents_caseId_idx": {
          "name": "documents_caseId_idx",
          "columns": [
            "caseId"
          ],
          "isUnique": false
        },
        "documents_userId_idx": {
          "name": "documents_userId_idx",
          "columns": [
            "userId"
          ],
          "isUnique": false
        }
      },
      "foreignKeys": {},
      "compositePrimaryKeys": {
        "documents_id": {
          "name": "documents_id",
          "columns": [
            "id"
          ]
        }
      },
      "uniqueConstraints": {},
      "checkConstraint": {}
    },
    "externalResources": {
      "name": "externalResources",
      "columns": {
        "id": {
          "name": "id",
          "type": "int",
          "primaryKey": false,
          "notNull": true,
          "autoincrement": true
        },
        "name": {
          "name": "name",
          "type": "varchar(255)",
          "primaryKey": false,
          "notNull": true,
          "autoincrement": false
        },
        "url": {
          "name": "url",
          "type": "varchar(512)",
          "primaryKey": false,
          "notNull": true,
          "autoincrement": false
        },
        "description": {
          "name": "description",
          "type": "text",
          "primaryKey": false,
          "notNull": false,
          "autoincrement": false
        },
        "resourceType": {
          "name": "resourceType",
          "type": "enum('Community','Informationsseite','Forum','Boykott-Initiative','Rechtliche Ressource')",
          "primaryKey": false,
          "notNull": true,
          "autoincrement": false
        },
        "isActive": {
          "name": "isActive",
          "type": "boolean",
          "primaryKey": false,
          "notNull": false,
          "autoincrement": false,
          "default": true
        },
        "createdAt": {
          "name": "createdAt",
          "type": "timestamp",
          "primaryKey": false,
          "notNull": true,
          "autoincrement": false,
          "default": "(now())"
        },
        "updatedAt": {
          "name": "updatedAt",
          "type": "timestamp",
          "primaryKey": false,
          "notNull": true,
          "autoincrement": false,
          "onUpdate": true,
          "default": "(now())"
        }
      },
      "indexes": {},
      "foreignKeys": {},
      "compositePrimaryKeys": {
        "externalResources_id": {
          "name": "externalResources_id",
          "columns": [
            "id"
          ]
        }
      },
      "uniqueConstraints": {},
      "checkConstraint": {}
    },
    "invoices": {
      "name": "invoices",
      "columns": {
        "id": {
          "name": "id",
          "type": "int",
          "primaryKey": false,
          "notNull": true,
          "autoincrement": true
        },
        "userId": {
          "name": "userId",
          "type": "int",
          "primaryKey": false,
          "notNull": true,
          "autoincrement": false
        },
        "stripeInvoiceId": {
          "name": "stripeInvoiceId",
          "type": "varchar(255)",
          "primaryKey": false,
          "notNull": true,
          "autoincrement": false
        },
        "stripeSubscriptionId": {
          "name": "stripeSubscriptionId",
          "type": "varchar(255)",
          "primaryKey": false,
          "notNull": false,
          "autoincrement": false
        },
        "amount": {
          "name": "amount",
          "type": "int",
          "primaryKey": false,
          "notNull": true,
          "autoincrement": false
        },
        "currency": {
          "name": "currency",
          "type": "varchar(3)",
          "primaryKey": false,
          "notNull": true,
          "autoincrement": false,
          "default": "'eur'"
        },
        "status": {
          "name": "status",
          "type": "enum('draft','open','paid','void','uncollectible')",
          "primaryKey": false,
          "notNull": true,
          "autoincrement": false
        },
        "paidAt": {
          "name": "paidAt",
          "type": "timestamp",
          "primaryKey": false,
          "notNull": false,
          "autoincrement": false
        },
        "dueDate": {
          "name": "dueDate",
          "type": "timestamp",
          "primaryKey": false,
          "notNull": false,
          "autoincrement": false
        },
        "createdAt": {
          "name": "createdAt",
          "type": "timestamp",
          "primaryKey": false,
          "notNull": true,
          "autoincrement": false,
          "default": "(now())"
        },
        "updatedAt": {
          "name": "updatedAt",
          "type": "timestamp",
          "primaryKey": false,
          "notNull": true,
          "autoincrement": false,
          "onUpdate": true,
          "default": "(now())"
        }
      },
      "indexes": {
        "invoices_userId_idx": {
          "name": "invoices_userId_idx",
          "columns": [
            "userId"
          ],
          "isUnique": false
        },
        "invoices_status_idx": {
          "name": "invoices_status_idx",
          "columns": [
            "status"
          ],
          "isUnique": false
        }
      },
      "foreignKeys": {},
      "compositePrimaryKeys": {
        "invoices_id": {
          "name": "invoices_id",
          "columns": [
            "id"
          ]
        }
      },
      "uniqueConstraints": {
        "invoices_stripeInvoiceId_unique": {
          "name": "invoices_stripeInvoiceId_unique",
          "columns": [
            "stripeInvoiceId"
          ]
        }
      },
      "checkConstraint": {}
    },
    "lawyerProfiles": {
      "name": "lawyerProfiles",
      "columns": {
        "id": {
          "name": "id",
          "type": "int",
          "primaryKey": false,
          "notNull": true,
          "autoincrement": true
        },
        "userId": {
          "name": "userId",
          "type": "int",
          "primaryKey": false,
          "notNull": true,
          "autoincrement": false
        },
        "firmName": {
          "name": "firmName",
          "type": "varchar(255)",
          "primaryKey": false,
          "notNull": false,
          "autoincrement": false
        },
        "location": {
          "name": "location",
          "type": "varchar(255)",
          "primaryKey": false,
          "notNull": false,
          "autoincrement": false
        },
        "phone": {
          "name": "phone",
          "type": "varchar(20)",
          "primaryKey": false,
          "notNull": false,
          "autoincrement": false
        },
        "website": {
          "name": "website",
          "type": "varchar(512)",
          "primaryKey": false,
          "notNull": false,
          "autoincrement": false
        },
        "specializations": {
          "name": "specializations",
          "type": "json",
          "primaryKey": false,
          "notNull": false,
          "autoincrement": false
        },
        "experience": {
          "name": "experience",
          "type": "int",
          "primaryKey": false,
          "notNull": false,
          "autoincrement": false
        },
        "rating": {
          "name": "rating",
          "type": "decimal(3,2)",
          "primaryKey": false,
          "notNull": false,
          "autoincrement": false
        },
        "reviewCount": {
          "name": "reviewCount",
          "type": "int",
          "primaryKey": false,
          "notNull": false,
          "autoincrement": false,
          "default": 0
        },
        "isVerified": {
          "name": "isVerified",
          "type": "boolean",
          "primaryKey": false,
          "notNull": false,
          "autoincrement": false,
          "default": false
        },
        "createdAt": {
          "name": "createdAt",
          "type": "timestamp",
          "primaryKey": false,
          "notNull": true,
          "autoincrement": false,
          "default": "(now())"
        },
        "updatedAt": {
          "name": "updatedAt",
          "type": "timestamp",
          "primaryKey": false,
          "notNull": true,
          "autoincrement": false,
          "onUpdate": true,
          "default": "(now())"
        }
      },
      "indexes": {
        "lawyerProfiles_userId_idx": {
          "name": "lawyerProfiles_userId_idx",
          "columns": [
            "userId"
          ],
          "isUnique": false
        }
      },
      "foreignKeys": {},
      "compositePrimaryKeys": {
        "lawyerProfiles_id": {
          "name": "lawyerProfiles_id",
          "columns": [
            "id"
          ]
        }
      },
      "uniqueConstraints": {
        "lawyerProfiles_userId_unique": {
          "name": "lawyerProfiles_userId_unique",
          "columns": [
            "userId"
          ]
        }
      },
      "checkConstraint": {}
    },
    "lawyerReviews": {
      "name": "lawyerReviews",
      "columns": {
        "id": {
          "name": "id",
          "type": "int",
          "primaryKey": false,
          "notNull": true,
          "autoincrement": true
        },
        "lawyerId": {
          "name": "lawyerId",
          "type": "int",
          "primaryKey": false,
          "notNull": true,
          "autoincrement": false
        },
        "userId": {
          "name": "userId",
          "type": "int",
          "primaryKey": false,
          "notNull": true,
          "autoincrement": false
        },
        "rating": {
          "name": "rating",
          "type": "int",
          "primaryKey": false,
          "notNull": true,
          "autoincrement": false
        },
        "comment": {
          "name": "comment",
          "type": "text",
          "primaryKey": false,
          "notNull": false,
          "autoincrement": false
        },
        "createdAt": {
          "name": "createdAt",
          "type": "timestamp",
          "primaryKey": false,
          "notNull": true,
          "autoincrement": false,
          "default": "(now())"
        }
      },
      "indexes": {
        "lawyerReviews_lawyerId_idx": {
          "name": "lawyerReviews_lawyerId_idx",
          "columns": [
            "lawyerId"
          ],
          "isUnique": false
        },
        "lawyerReviews_userId_idx": {
          "name": "lawyerReviews_userId_idx",
          "columns": [
            "userId"
          ],
          "isUnique": false
        }
      },
      "foreignKeys": {},
      "compositePrimaryKeys": {
        "lawyerReviews_id": {
          "name": "lawyerReviews_id",
          "columns": [
            "id"
          ]
        }
      },
      "uniqueConstraints": {},
      "checkConstraint": {}
    },
    "newsletterIssues": {
      "name": "newsletterIssues",
      "columns": {
        "id": {
          "name": "id",
          "type": "int",
          "primaryKey": false,
          "notNull": true,
          "autoincrement": true
        },
        "subject": {
          "name": "subject",
          "type": "varchar(255)",
          "primaryKey": false,
          "notNull": true,
          "autoincrement": false
        },
        "content": {
          "name": "content",
          "type": "text",
          "primaryKey": false,
          "notNull": true,
          "autoincrement": false
        },
        "issueNumber": {
          "name": "issueNumber",
          "type": "int",
          "primaryKey": false,
          "notNull": false,
          "autoincrement": false
        },
        "sentAt": {
          "name": "sentAt",
          "type": "timestamp",
          "primaryKey": false,
          "notNull": false,
          "autoincrement": false
        },
        "createdAt": {
          "name": "createdAt",
          "type": "timestamp",
          "primaryKey": false,
          "notNull": true,
          "autoincrement": false,
          "default": "(now())"
        },
        "updatedAt": {
          "name": "updatedAt",
          "type": "timestamp",
          "primaryKey": false,
          "notNull": true,
          "autoincrement": false,
          "onUpdate": true,
          "default": "(now())"
        }
      },
      "indexes": {},
      "foreignKeys": {},
      "compositePrimaryKeys": {
        "newsletterIssues_id": {
          "name": "newsletterIssues_id",
          "columns": [
            "id"
          ]
        }
      },
      "uniqueConstraints": {},
      "checkConstraint": {}
    },
    "newsletterSubscriptions": {
      "name": "newsletterSubscriptions",
      "columns": {
        "id": {
          "name": "id",
          "type": "int",
          "primaryKey": false,
          "notNull": true,
          "autoincrement": true
        },
        "userId": {
          "name": "userId",
          "type": "int",
          "primaryKey": false,
          "notNull": true,
          "autoincrement": false
        },
        "email": {
          "name": "email",
          "type": "varchar(320)",
          "primaryKey": false,
          "notNull": true,
          "autoincrement": false
        },
        "isSubscribed": {
          "name": "isSubscribed",
          "type": "boolean",
          "primaryKey": false,
          "notNull": false,
          "autoincrement": false,
          "default": true
        },
        "createdAt": {
          "name": "createdAt",
          "type": "timestamp",
          "primaryKey": false,
          "notNull": true,
          "autoincrement": false,
          "default": "(now())"
        },
        "updatedAt": {
          "name": "updatedAt",
          "type": "timestamp",
          "primaryKey": false,
          "notNull": true,
          "autoincrement": false,
          "onUpdate": true,
          "default": "(now())"
        }
      },
      "indexes": {
        "newsletterSubscriptions_userId_idx": {
          "name": "newsletterSubscriptions_userId_idx",
          "columns": [
            "userId"
          ],
          "isUnique": false
        },
        "newsletterSubscriptions_email_idx": {
          "name": "newsletterSubscriptions_email_idx",
          "columns": [
            "email"
          ],
          "isUnique": false
        }
      },
      "foreignKeys": {},
      "compositePrimaryKeys": {
        "newsletterSubscriptions_id": {
          "name": "newsletterSubscriptions_id",
          "columns": [
            "id"
          ]
        }
      },
      "uniqueConstraints": {},
      "checkConstraint": {}
    },
    "paymentTransactions": {
      "name": "paymentTransactions",
      "columns": {
        "id": {
          "name": "id",
          "type": "int",
          "primaryKey": false,
          "notNull": true,
          "autoincrement": true
        },
        "userId": {
          "name": "userId",
          "type": "int",
          "primaryKey": false,
          "notNull": true,
          "autoincrement": false
        },
        "stripePaymentIntentId": {
          "name": "stripePaymentIntentId",
          "type": "varchar(255)",
          "primaryKey": false,
          "notNull": true,
          "autoincrement": false
        },
        "amount": {
          "name": "amount",
          "type": "int",
          "primaryKey": false,
          "notNull": true,
          "autoincrement": false
        },
        "currency": {
          "name": "currency",
          "type": "varchar(3)",
          "primaryKey": false,
          "notNull": true,
          "autoincrement": false,
          "default": "'eur'"
        },
        "status": {
          "name": "status",
          "type": "enum('pending','succeeded','failed','canceled')",
          "primaryKey": false,
          "notNull": true,
          "autoincrement": false
        },
        "description": {
          "name": "description",
          "type": "varchar(512)",
          "primaryKey": false,
          "notNull": false,
          "autoincrement": false
        },
        "metadata": {
          "name": "metadata",
          "type": "json",
          "primaryKey": false,
          "notNull": false,
          "autoincrement": false
        },
        "createdAt": {
          "name": "createdAt",
          "type": "timestamp",
          "primaryKey": false,
          "notNull": true,
          "autoincrement": false,
          "default": "(now())"
        },
        "updatedAt": {
          "name": "updatedAt",
          "type": "timestamp",
          "primaryKey": false,
          "notNull": true,
          "autoincrement": false,
          "onUpdate": true,
          "default": "(now())"
        }
      },
      "indexes": {
        "paymentTransactions_userId_idx": {
          "name": "paymentTransactions_userId_idx",
          "columns": [
            "userId"
          ],
          "isUnique": false
        },
        "paymentTransactions_status_idx": {
          "name": "paymentTransactions_status_idx",
          "columns": [
            "status"
          ],
          "isUnique": false
        }
      },
      "foreignKeys": {},
      "compositePrimaryKeys": {
        "paymentTransactions_id": {
          "name": "paymentTransactions_id",
          "columns": [
            "id"
          ]
        }
      },
      "uniqueConstraints": {
        "paymentTransactions_stripePaymentIntentId_unique": {
          "name": "paymentTransactions_stripePaymentIntentId_unique",
          "columns": [
            "stripePaymentIntentId"
          ]
        }
      },
      "checkConstraint": {}
    },
    "pollVotes": {
      "name": "pollVotes",
      "columns": {
        "id": {
          "name": "id",
          "type": "int",
          "primaryKey": false,
          "notNull": true,
          "autoincrement": true
        },
        "pollId": {
          "name": "pollId",
          "type": "int",
          "primaryKey": false,
          "notNull": true,
          "autoincrement": false
        },
        "userId": {
          "name": "userId",
          "type": "int",
          "primaryKey": false,
          "notNull": true,
          "autoincrement": false
        },
        "selectedOption": {
          "name": "selectedOption",
          "type": "varchar(255)",
          "primaryKey": false,
          "notNull": true,
          "autoincrement": false
        },
        "createdAt": {
          "name": "createdAt",
          "type": "timestamp",
          "primaryKey": false,
          "notNull": true,
          "autoincrement": false,
          "default": "(now())"
        }
      },
      "indexes": {
        "pollVotes_pollId_idx": {
          "name": "pollVotes_pollId_idx",
          "columns": [
            "pollId"
          ],
          "isUnique": false
        },
        "pollVotes_userId_idx": {
          "name": "pollVotes_userId_idx",
          "columns": [
            "userId"
          ],
          "isUnique": false
        }
      },
      "foreignKeys": {},
      "compositePrimaryKeys": {
        "pollVotes_id": {
          "name": "pollVotes_id",
          "columns": [
            "id"
          ]
        }
      },
      "uniqueConstraints": {},
      "checkConstraint": {}
    },
    "polls": {
      "name": "polls",
      "columns": {
        "id": {
          "name": "id",
          "type": "int",
          "primaryKey": false,
          "notNull": true,
          "autoincrement": true
        },
        "createdBy": {
          "name": "createdBy",
          "type": "int",
          "primaryKey": false,
          "notNull": true,
          "autoincrement": false
        },
        "title": {
          "name": "title",
          "type": "varchar(255)",
          "primaryKey": false,
          "notNull": true,
          "autoincrement": false
        },
        "description": {
          "name": "description",
          "type": "text",
          "primaryKey": false,
          "notNull": false,
          "autoincrement": false
        },
        "pollType": {
          "name": "pollType",
          "type": "enum('Ja/Nein','Multiple Choice','Ranking','Tier-Umfrage')",
          "primaryKey": false,
          "notNull": true,
          "autoincrement": false
        },
        "options": {
          "name": "options",
          "type": "json",
          "primaryKey": false,
          "notNull": false,
          "autoincrement": false
        },
        "isActive": {
          "name": "isActive",
          "type": "boolean",
          "primaryKey": false,
          "notNull": false,
          "autoincrement": false,
          "default": true
        },
        "totalVotes": {
          "name": "totalVotes",
          "type": "int",
          "primaryKey": false,
          "notNull": false,
          "autoincrement": false,
          "default": 0
        },
        "createdAt": {
          "name": "createdAt",
          "type": "timestamp",
          "primaryKey": false,
          "notNull": true,
          "autoincrement": false,
          "default": "(now())"
        },
        "updatedAt": {
          "name": "updatedAt",
          "type": "timestamp",
          "primaryKey": false,
          "notNull": true,
          "autoincrement": false,
          "onUpdate": true,
          "default": "(now())"
        }
      },
      "indexes": {
        "polls_createdBy_idx": {
          "name": "polls_createdBy_idx",
          "columns": [
            "createdBy"
          ],
          "isUnique": false
        }
      },
      "foreignKeys": {},
      "compositePrimaryKeys": {
        "polls_id": {
          "name": "polls_id",
          "columns": [
            "id"
          ]
        }
      },
      "uniqueConstraints": {},
      "checkConstraint": {}
    },
    "promoCodes": {
      "name": "promoCodes",
      "columns": {
        "id": {
          "name": "id",
          "type": "int",
          "primaryKey": false,
          "notNull": true,
          "autoincrement": true
        },
        "stripePromotionCodeId": {
          "name": "stripePromotionCodeId",
          "type": "varchar(255)",
          "primaryKey": false,
          "notNull": true,
          "autoincrement": false
        },
        "stripeCouponId": {
          "name": "stripeCouponId",
          "type": "varchar(255)",
          "primaryKey": false,
          "notNull": true,
          "autoincrement": false
        },
        "code": {
          "name": "code",
          "type": "varchar(100)",
          "primaryKey": false,
          "notNull": true,
          "autoincrement": false
        },
        "description": {
          "name": "description",
          "type": "varchar(255)",
          "primaryKey": false,
          "notNull": false,
          "autoincrement": false
        },
        "isActive": {
          "name": "isActive",
          "type": "boolean",
          "primaryKey": false,
          "notNull": false,
          "autoincrement": false,
          "default": true
        },
        "createdAt": {
          "name": "createdAt",
          "type": "timestamp",
          "primaryKey": false,
          "notNull": true,
          "autoincrement": false,
          "default": "(now())"
        }
      },
      "indexes": {},
      "foreignKeys": {},
      "compositePrimaryKeys": {
        "promoCodes_id": {
          "name": "promoCodes_id",
          "columns": [
            "id"
          ]
        }
      },
      "uniqueConstraints": {
        "promoCodes_stripePromotionCodeId_unique": {
          "name": "promoCodes_stripePromotionCodeId_unique",
          "columns": [
            "stripePromotionCodeId"
          ]
        },
        "promoCodes_code_unique": {
          "name": "promoCodes_code_unique",
          "columns": [
            "code"
          ]
        }
      },
      "checkConstraint": {}
    },
    "stripePrices": {
      "name": "stripePrices",
      "columns": {
        "id": {
          "name": "id",
          "type": "int",
          "primaryKey": false,
          "notNull": true,
          "autoincrement": true
        },
        "stripePriceId": {
          "name": "stripePriceId",
          "type": "varchar(255)",
          "primaryKey": false,
          "notNull": true,
          "autoincrement": false
        },
        "stripeProductId": {
          "name": "stripeProductId",
          "type": "varchar(255)",
          "primaryKey": false,
          "notNull": true,
          "autoincrement": false
        },
        "amount": {
          "name": "amount",
          "type": "int",
          "primaryKey": false,
          "notNull": true,
          "autoincrement": false
        },
        "currency": {
          "name": "currency",
          "type": "varchar(3)",
          "primaryKey": false,
          "notNull": true,
          "autoincrement": false,
          "default": "'eur'"
        },
        "interval": {
          "name": "interval",
          "type": "enum('one_time','month','year')",
          "primaryKey": false,
          "notNull": true,
          "autoincrement": false
        },
        "isActive": {
          "name": "isActive",
          "type": "boolean",
          "primaryKey": false,
          "notNull": false,
          "autoincrement": false,
          "default": true
        },
        "createdAt": {
          "name": "createdAt",
          "type": "timestamp",
          "primaryKey": false,
          "notNull": true,
          "autoincrement": false,
          "default": "(now())"
        }
      },
      "indexes": {
        "stripePrices_stripeProductId_idx": {
          "name": "stripePrices_stripeProductId_idx",
          "columns": [
            "stripeProductId"
          ],
          "isUnique": false
        }
      },
      "foreignKeys": {},
      "compositePrimaryKeys": {
        "stripePrices_id": {
          "name": "stripePrices_id",
          "columns": [
            "id"
          ]
        }
      },
      "uniqueConstraints": {
        "stripePrices_stripePriceId_unique": {
          "name": "stripePrices_stripePriceId_unique",
          "columns": [
            "stripePriceId"
          ]
        }
      },
      "checkConstraint": {}
    },
    "stripeProducts": {
      "name": "stripeProducts",
      "columns": {
        "id": {
          "name": "id",
          "type": "int",
          "primaryKey": false,
          "notNull": true,
          "autoincrement": true
        },
        "stripeProductId": {
          "name": "stripeProductId",
          "type": "varchar(255)",
          "primaryKey": false,
          "notNull": true,
          "autoincrement": false
        },
        "name": {
          "name": "name",
          "type": "varchar(255)",
          "primaryKey": false,
          "notNull": true,
          "autoincrement": false
        },
        "description": {
          "name": "description",
          "type": "text",
          "primaryKey": false,
          "notNull": false,
          "autoincrement": false
        },
        "category": {
          "name": "category",
          "type": "enum('lawyer_consultation','premium_feature','document_package','subscription','other')",
          "primaryKey": false,
          "notNull": true,
          "autoincrement": false
        },
        "isActive": {
          "name": "isActive",
          "type": "boolean",
          "primaryKey": false,
          "notNull": false,
          "autoincrement": false,
          "default": true
        },
        "createdAt": {
          "name": "createdAt",
          "type": "timestamp",
          "primaryKey": false,
          "notNull": true,
          "autoincrement": false,
          "default": "(now())"
        },
        "updatedAt": {
          "name": "updatedAt",
          "type": "timestamp",
          "primaryKey": false,
          "notNull": true,
          "autoincrement": false,
          "onUpdate": true,
          "default": "(now())"
        }
      },
      "indexes": {},
      "foreignKeys": {},
      "compositePrimaryKeys": {
        "stripeProducts_id": {
          "name": "stripeProducts_id",
          "columns": [
            "id"
          ]
        }
      },
      "uniqueConstraints": {
        "stripeProducts_stripeProductId_unique": {
          "name": "stripeProducts_stripeProductId_unique",
          "columns": [
            "stripeProductId"
          ]
        }
      },
      "checkConstraint": {}
    },
    "userSubscriptions": {
      "name": "userSubscriptions",
      "columns": {
        "id": {
          "name": "id",
          "type": "int",
          "primaryKey": false,
          "notNull": true,
          "autoincrement": true
        },
        "userId": {
          "name": "userId",
          "type": "int",
          "primaryKey": false,
          "notNull": true,
          "autoincrement": false
        },
        "stripeSubscriptionId": {
          "name": "stripeSubscriptionId",
          "type": "varchar(255)",
          "primaryKey": false,
          "notNull": true,
          "autoincrement": false
        },
        "stripePriceId": {
          "name": "stripePriceId",
          "type": "varchar(255)",
          "primaryKey": false,
          "notNull": true,
          "autoincrement": false
        },
        "status": {
          "name": "status",
          "type": "enum('active','paused','canceled','past_due')",
          "primaryKey": false,
          "notNull": true,
          "autoincrement": false
        },
        "currentPeriodStart": {
          "name": "currentPeriodStart",
          "type": "timestamp",
          "primaryKey": false,
          "notNull": false,
          "autoincrement": false
        },
        "currentPeriodEnd": {
          "name": "currentPeriodEnd",
          "type": "timestamp",
          "primaryKey": false,
          "notNull": false,
          "autoincrement": false
        },
        "canceledAt": {
          "name": "canceledAt",
          "type": "timestamp",
          "primaryKey": false,
          "notNull": false,
          "autoincrement": false
        },
        "createdAt": {
          "name": "createdAt",
          "type": "timestamp",
          "primaryKey": false,
          "notNull": true,
          "autoincrement": false,
          "default": "(now())"
        },
        "updatedAt": {
          "name": "updatedAt",
          "type": "timestamp",
          "primaryKey": false,
          "notNull": true,
          "autoincrement": false,
          "onUpdate": true,
          "default": "(now())"
        }
      },
      "indexes": {
        "userSubscriptions_userId_idx": {
          "name": "userSubscriptions_userId_idx",
          "columns": [
            "userId"
          ],
          "isUnique": false
        },
        "userSubscriptions_status_idx": {
          "name": "userSubscriptions_status_idx",
          "columns": [
            "status"
          ],
          "isUnique": false
        }
      },
      "foreignKeys": {},
      "compositePrimaryKeys": {
        "userSubscriptions_id": {
          "name": "userSubscriptions_id",
          "columns": [
            "id"
          ]
        }
      },
      "uniqueConstraints": {
        "userSubscriptions_stripeSubscriptionId_unique": {
          "name": "userSubscriptions_stripeSubscriptionId_unique",
          "columns": [
            "stripeSubscriptionId"
          ]
        }
      },
      "checkConstraint": {}
    },
    "users": {
      "name": "users",
      "columns": {
        "id": {
          "name": "id",
          "type": "int",
          "primaryKey": false,
          "notNull": true,
          "autoincrement": true
        },
        "openId": {
          "name": "openId",
          "type": "varchar(64)",
          "primaryKey": false,
          "notNull": true,
          "autoincrement": false
        },
        "name": {
          "name": "name",
          "type": "text",
          "primaryKey": false,
          "notNull": false,
          "autoincrement": false
        },
        "email": {
          "name": "email",
          "type": "varchar(320)",
          "primaryKey": false,
          "notNull": false,
          "autoincrement": false
        },
        "loginMethod": {
          "name": "loginMethod",
          "type": "varchar(64)",
          "primaryKey": false,
          "notNull": false,
          "autoincrement": false
        },
        "role": {
          "name": "role",
          "type": "enum('user','admin','lawyer','moderator')",
          "primaryKey": false,
          "notNull": true,
          "autoincrement": false,
          "default": "'user'"
        },
        "bio": {
          "name": "bio",
          "type": "text",
          "primaryKey": false,
          "notNull": false,
          "autoincrement": false
        },
        "avatar": {
          "name": "avatar",
          "type": "varchar(512)",
          "primaryKey": false,
          "notNull": false,
          "autoincrement": false
        },
        "isLawyer": {
          "name": "isLawyer",
          "type": "boolean",
          "primaryKey": false,
          "notNull": false,
          "autoincrement": false,
          "default": false
        },
        "lawyerSpecializations": {
          "name": "lawyerSpecializations",
          "type": "json",
          "primaryKey": false,
          "notNull": false,
          "autoincrement": false
        },
        "lawyerContact": {
          "name": "lawyerContact",
          "type": "varchar(255)",
          "primaryKey": false,
          "notNull": false,
          "autoincrement": false
        },
        "isOpinionLeader": {
          "name": "isOpinionLeader",
          "type": "boolean",
          "primaryKey": false,
          "notNull": false,
          "autoincrement": false,
          "default": false
        },
        "opinionLeaderBio": {
          "name": "opinionLeaderBio",
          "type": "text",
          "primaryKey": false,
          "notNull": false,
          "autoincrement": false
        },
        "argumentPosition": {
          "name": "argumentPosition",
          "type": "int",
          "primaryKey": false,
          "notNull": false,
          "autoincrement": false
        },
        "stripeCustomerId": {
          "name": "stripeCustomerId",
          "type": "varchar(255)",
          "primaryKey": false,
          "notNull": false,
          "autoincrement": false
        },
        "createdAt": {
          "name": "createdAt",
          "type": "timestamp",
          "primaryKey": false,
          "notNull": true,
          "autoincrement": false,
          "default": "(now())"
        },
        "updatedAt": {
          "name": "updatedAt",
          "type": "timestamp",
          "primaryKey": false,
          "notNull": true,
          "autoincrement": false,
          "onUpdate": true,
          "default": "(now())"
        },
        "lastSignedIn": {
          "name": "lastSignedIn",
          "type": "timestamp",
          "primaryKey": false,
          "notNull": true,
          "autoincrement": false,
          "default": "(now())"
        }
      },
      "indexes": {
        "email_idx": {
          "name": "email_idx",
          "columns": [
            "email"
          ],
          "isUnique": false
        },
        "role_idx": {
          "name": "role_idx",
          "columns": [
            "role"
          ],
          "isUnique": false
        }
      },
      "foreignKeys": {},
      "compositePrimaryKeys": {
        "users_id": {
          "name": "users_id",
          "columns": [
            "id"
          ]
        }
      },
      "uniqueConstraints": {
        "users_openId_unique": {
          "name": "users_openId_unique",
          "columns": [
            "openId"
          ]
        },
        "users_email_unique": {
          "name": "users_email_unique",
          "columns": [
            "email"
          ]
        },
        "users_stripeCustomerId_unique": {
          "name": "users_stripeCustomerId_unique",
          "columns": [
            "stripeCustomerId"
          ]
        }
      },
      "checkConstraint": {}
    },
    "wikiArticles": {
      "name": "wikiArticles",
      "columns": {
        "id": {
          "name": "id",
          "type": "int",
          "primaryKey": false,
          "notNull": true,
          "autoincrement": true
        },
        "createdBy": {
          "name": "createdBy",
          "type": "int",
          "primaryKey": false,
          "notNull": true,
          "autoincrement": false
        },
        "title": {
          "name": "title",
          "type": "varchar(255)",
          "primaryKey": false,
          "notNull": true,
          "autoincrement": false
        },
        "slug": {
          "name": "slug",
          "type": "varchar(255)",
          "primaryKey": false,
          "notNull": false,
          "autoincrement": false
        },
        "content": {
          "name": "content",
          "type": "text",
          "primaryKey": false,
          "notNull": true,
          "autoincrement": false
        },
        "category": {
          "name": "category",
          "type": "varchar(100)",
          "primaryKey": false,
          "notNull": false,
          "autoincrement": false
        },
        "tags": {
          "name": "tags",
          "type": "json",
          "primaryKey": false,
          "notNull": false,
          "autoincrement": false
        },
        "isPublished": {
          "name": "isPublished",
          "type": "boolean",
          "primaryKey": false,
          "notNull": false,
          "autoincrement": false,
          "default": false
        },
        "views": {
          "name": "views",
          "type": "int",
          "primaryKey": false,
          "notNull": false,
          "autoincrement": false,
          "default": 0
        },
        "createdAt": {
          "name": "createdAt",
          "type": "timestamp",
          "primaryKey": false,
          "notNull": true,
          "autoincrement": false,
          "default": "(now())"
        },
        "updatedAt": {
          "name": "updatedAt",
          "type": "timestamp",
          "primaryKey": false,
          "notNull": true,
          "autoincrement": false,
          "onUpdate": true,
          "default": "(now())"
        }
      },
      "indexes": {
        "wikiArticles_createdBy_idx": {
          "name": "wikiArticles_createdBy_idx",
          "columns": [
            "createdBy"
          ],
          "isUnique": false
        },
        "wikiArticles_slug_idx": {
          "name": "wikiArticles_slug_idx",
          "columns": [
            "slug"
          ],
          "isUnique": false
        }
      },
      "foreignKeys": {},
      "compositePrimaryKeys": {
        "wikiArticles_id": {
          "name": "wikiArticles_id",
          "columns": [
            "id"
          ]
        }
      },
      "uniqueConstraints": {
        "wikiArticles_slug_unique": {
          "name": "wikiArticles_slug_unique",
          "columns": [
            "slug"
          ]
        }
      },
      "checkConstraint": {}
    },
    "wordCloudData": {
      "name": "wordCloudData",
      "columns": {
        "id": {
          "name": "id",
          "type": "int",
          "primaryKey": false,
          "notNull": true,
          "autoincrement": true
        },
        "word": {
          "name": "word",
          "type": "varchar(255)",
          "primaryKey": false,
          "notNull": true,
          "autoincrement": false
        },
        "frequency": {
          "name": "frequency",
          "type": "int",
          "primaryKey": false,
          "notNull": false,
          "autoincrement": false,
          "default": 1
        },
        "sentiment": {
          "name": "sentiment",
          "type": "enum('positiv','neutral','negativ')",
          "primaryKey": false,
          "notNull": false,
          "autoincrement": false
        },
        "category": {
          "name": "category",
          "type": "varchar(100)",
          "primaryKey": false,
          "notNull": false,
          "autoincrement": false
        },
        "lastUpdated": {
          "name": "lastUpdated",
          "type": "timestamp",
          "primaryKey": false,
          "notNull": true,
          "autoincrement": false,
          "onUpdate": true,
          "default": "(now())"
        }
      },
      "indexes": {
        "wordCloudData_word_idx": {
          "name": "wordCloudData_word_idx",
          "columns": [
            "word"
          ],
          "isUnique": false
        }
      },
      "foreignKeys": {},
      "compositePrimaryKeys": {
        "wordCloudData_id": {
          "name": "wordCloudData_id",
          "columns": [
            "id"
          ]
        }
      },
      "uniqueConstraints": {
        "wordCloudData_word_unique": {
          "name": "wordCloudData_word_unique",
          "columns": [
            "word"
          ]
        }
      },
      "checkConstraint": {}
    }
  },
  "views": {},
  "_meta": {
    "schemas": {},
    "tables": {},
    "columns": {}
  },
  "internal": {
    "tables": {},
    "indexes": {}
  }
}